pycfdns/__init__.py
pycfdns/const.py
pycfdns/exceptions.py
pycfdns/models.py
pycfdns-2.0.1.dist-info/LICENSE
pycfdns-2.0.1.dist-info/METADATA
pycfdns-2.0.1.dist-info/WHEEL
pycfdns-2.0.1.dist-info/top_level.txt
pycfdns-2.0.1.dist-info/RECORD
