Metadata-Version: 2.1
Name: pycfdns
Version: 2.0.1
Summary: Update Cloudflare DNS records.
Home-page: https://github.com/ludeeus/pycfdns
Author: Joakim Sorensen
Author-email: hi@ludeeus.dev
Classifier: Programming Language :: Python :: 3
Classifier: License :: OSI Approved :: MIT License
Classifier: Operating System :: OS Independent
License-File: LICENSE
Requires-Dist: aiohttp (<4.0,>=3.6.1)
